pyapso/__init__.py
pyapso/pyapso.py
pyapso-1.1.0.dist-info/licenses/LICENSE
pyapso-1.1.0.dist-info/METADATA
pyapso-1.1.0.dist-info/WHEEL
pyapso-1.1.0.dist-info/top_level.txt
pyapso-1.1.0.dist-info/RECORD
