Metadata-Version: 2.4
Name: PyApso
Version: 1.1.0
Summary: Adaptive Particle Swarm Optimization for continuous, multi-objective, and multidimensional problems
Home-page: https://github.com/smohamadabedy/pyapso
Project-URL: Homepage, https://github.com/smohamadabedy/pyapso
Project-URL: Documentation, https://github.com/smohamadabedy/pyapso#readme
Project-URL: Source, https://github.com/smohamadabedy/pyapso
Project-URL: Issues, https://github.com/smohamadabedy/pyapso/issues
Keywords: optimization,particle swarm optimization,APSO,metaheuristic
License-File: LICENSE
Requires-Dist: numpy
Requires-Dist: tqdm
Requires-Dist: matplotlib
Dynamic: home-page
Dynamic: license-file
